servefs/__main__.py
servefs/cli.py
servefs/config.py
servefs/main.py
servefs/middleware/auth.py
servefs/routes/api.py
servefs/routes/page.py
servefs/static/cdn_cache/14b2812c4b916ea2a2a456f902a53453.js
servefs/static/cdn_cache/2850c9d21729fcbdf74980f7e3cebeab.js
servefs/static/cdn_cache/2a3463ed14a211faeaa1bc9653007d64.css
servefs/static/cdn_cache/774694f80354f4570a7979bff5b594be.js
servefs/static/cdn_cache/a954d0a080ffdeed2e828ed2ab246353.js
servefs/static/cdn_cache/e142eceeaa6e9b1c010da7468aacc153.js
servefs/static/css/style.css
servefs/static/favicon.ico
servefs/static/favicon.webp
servefs/static/index.html
servefs/static/js/index.js
servefs/utils/cdn_cache.py
servefs/utils/network.py
servefs/utils/static.py
servefs-0.2.5.dist-info/METADATA
servefs-0.2.5.dist-info/WHEEL
servefs-0.2.5.dist-info/entry_points.txt
servefs-0.2.5.dist-info/RECORD
